reporter/__init__.py
reporter/base.py
reporter/client.py
reporter/exceptions.py
reporter/helpers.py
reporter/mixins.py
reporter/object_includes.py
reporter/objects/__init__.py
reporter/objects/activity.py
reporter/objects/assessment.py
reporter/objects/assessment_comment.py
reporter/objects/assessment_phase.py
reporter/objects/assessment_section.py
reporter/objects/assessment_section_comment.py
reporter/objects/assessment_template.py
reporter/objects/assessment_user.py
reporter/objects/auto_assignment.py
reporter/objects/client.py
reporter/objects/custom_field.py
reporter/objects/document.py
reporter/objects/finding.py
reporter/objects/finding_comment.py
reporter/objects/finding_created_event.py
reporter/objects/finding_event.py
reporter/objects/finding_import_event.py
reporter/objects/finding_layout.py
reporter/objects/finding_layout_field.py
reporter/objects/finding_published_event.py
reporter/objects/finding_resolver_event.py
reporter/objects/finding_retest.py
reporter/objects/finding_retest_cancelled_event.py
reporter/objects/finding_retest_inquiry.py
reporter/objects/finding_review_event.py
reporter/objects/finding_status_change.py
reporter/objects/finding_template.py
reporter/objects/language.py
reporter/objects/output_file.py
reporter/objects/reaction.py
reporter/objects/report_page.py
reporter/objects/role.py
reporter/objects/target.py
reporter/objects/task.py
reporter/objects/task_set.py
reporter/objects/test_case.py
reporter/objects/theme.py
reporter/objects/tool_finding.py
reporter/objects/tool_finding_target_info.py
reporter/objects/tool_target.py
reporter/objects/user.py
reporter/objects/user_group.py
reporter/objects/webhook.py
reporter/py.typed
reporter/types.py
securityreporter-1.4.0.dist-info/LICENSE
securityreporter-1.4.0.dist-info/METADATA
securityreporter-1.4.0.dist-info/WHEEL
securityreporter-1.4.0.dist-info/RECORD
