Metadata-Version: 2.1
Name: securityreporter
Version: 1.4.0
Summary: A Python wrapper for the Reporter API.
Home-page: https://securityreporter.app/
Author: Alexander Krigsman
Author-email: alexander.krigsman@dongit.nl
Maintainer: Stefan van der Lugt
Maintainer-email: stefan.vanderlugt@dongit.nl
Requires-Python: >=3.10.0,<4.0.0
Classifier: Programming Language :: Python :: 3
Classifier: Programming Language :: Python :: 3.10
Classifier: Programming Language :: Python :: 3.11
Classifier: Programming Language :: Python :: 3.12
Requires-Dist: requests (>=2.32.3,<3.0.0)
Project-URL: Documentation, https://python-reporter.readthedocs.io/
Project-URL: Repository, https://github.com/dongit-org/python-reporter
